{
  "variable": "PM 10",
  "fecha_generacion": "2026-02-16 13:00:18",
  "modelo": "SARIMA(1, 0, 1)(0, 1, 1, 12)",
  "aic": 758.7906269906852,
  "observaciones_historicas": 183,
  "horas_pronostico": 72,
  "limite_permitido": 75,
  "historico": [
    {
      "fecha": "2026-02-08 17:00:00",
      "valor": 10.0
    },
    {
      "fecha": "2026-02-08 18:00:00",
      "valor": 8.333333333333334
    },
    {
      "fecha": "2026-02-08 19:00:00",
      "valor": 9.5
    },
    {
      "fecha": "2026-02-08 20:00:00",
      "valor": 10.833333333333334
    },
    {
      "fecha": "2026-02-08 21:00:00",
      "valor": 9.0
    },
    {
      "fecha": "2026-02-08 22:00:00",
      "valor": 8.666666666666666
    },
    {
      "fecha": "2026-02-08 23:00:00",
      "valor": 6.5
    },
    {
      "fecha": "2026-02-09 00:00:00",
      "valor": 9.166666666666666
    },
    {
      "fecha": "2026-02-09 01:00:00",
      "valor": 10.2
    },
    {
      "fecha": "2026-02-09 02:00:00",
      "valor": 13.666666666666666
    },
    {
      "fecha": "2026-02-09 03:00:00",
      "valor": 11.833333333333334
    },
    {
      "fecha": "2026-02-09 04:00:00",
      "valor": 11.333333333333334
    },
    {
      "fecha": "2026-02-09 05:00:00",
      "valor": 10.333333333333334
    },
    {
      "fecha": "2026-02-09 06:00:00",
      "valor": 9.0
    },
    {
      "fecha": "2026-02-09 07:00:00",
      "valor": 7.166666666666667
    },
    {
      "fecha": "2026-02-09 08:00:00",
      "valor": 10.0
    },
    {
      "fecha": "2026-02-09 09:00:00",
      "valor": 13.333333333333334
    },
    {
      "fecha": "2026-02-09 10:00:00",
      "valor": 13.666666666666666
    },
    {
      "fecha": "2026-02-09 11:00:00",
      "valor": 21.333333333333332
    },
    {
      "fecha": "2026-02-09 12:00:00",
      "valor": 31.8
    },
    {
      "fecha": "2026-02-09 13:00:00",
      "valor": 23.833333333333332
    },
    {
      "fecha": "2026-02-09 14:00:00",
      "valor": 18.0
    },
    {
      "fecha": "2026-02-09 15:00:00",
      "valor": 16.0
    },
    {
      "fecha": "2026-02-09 16:00:00",
      "valor": 18.0
    },
    {
      "fecha": "2026-02-09 17:00:00",
      "valor": 12.833333333333334
    },
    {
      "fecha": "2026-02-09 18:00:00",
      "valor": 9.833333333333334
    },
    {
      "fecha": "2026-02-09 19:00:00",
      "valor": 8.333333333333334
    },
    {
      "fecha": "2026-02-09 20:00:00",
      "valor": 7.5
    },
    {
      "fecha": "2026-02-09 21:00:00",
      "valor": 8.166666666666666
    },
    {
      "fecha": "2026-02-09 22:00:00",
      "valor": 12.5
    },
    {
      "fecha": "2026-02-09 23:00:00",
      "valor": 12.6
    },
    {
      "fecha": "2026-02-10 00:00:00",
      "valor": 14.0
    },
    {
      "fecha": "2026-02-10 01:00:00",
      "valor": 14.5
    },
    {
      "fecha": "2026-02-10 02:00:00",
      "valor": 10.5
    },
    {
      "fecha": "2026-02-10 03:00:00",
      "valor": 12.5
    },
    {
      "fecha": "2026-02-10 04:00:00",
      "valor": 7.666666666666667
    },
    {
      "fecha": "2026-02-10 05:00:00",
      "valor": 8.5
    },
    {
      "fecha": "2026-02-10 06:00:00",
      "valor": 9.833333333333334
    },
    {
      "fecha": "2026-02-10 07:00:00",
      "valor": 8.833333333333334
    },
    {
      "fecha": "2026-02-10 08:00:00",
      "valor": 9.6
    },
    {
      "fecha": "2026-02-10 09:00:00",
      "valor": 5.833333333333333
    },
    {
      "fecha": "2026-02-10 10:00:00",
      "valor": 9.0
    },
    {
      "fecha": "2026-02-10 11:00:00",
      "valor": 15.8
    },
    {
      "fecha": "2026-02-10 12:00:00",
      "valor": 9.333333333333334
    },
    {
      "fecha": "2026-02-10 13:00:00",
      "valor": 7.5
    },
    {
      "fecha": "2026-02-10 14:00:00",
      "valor": 9.666666666666666
    },
    {
      "fecha": "2026-02-10 15:00:00",
      "valor": 9.2
    },
    {
      "fecha": "2026-02-10 16:00:00",
      "valor": 8.0
    },
    {
      "fecha": "2026-02-10 17:00:00",
      "valor": 3.8333333333333335
    },
    {
      "fecha": "2026-02-10 18:00:00",
      "valor": 3.6666666666666665
    },
    {
      "fecha": "2026-02-10 19:00:00",
      "valor": 6.333333333333333
    },
    {
      "fecha": "2026-02-10 20:00:00",
      "valor": 3.5
    },
    {
      "fecha": "2026-02-10 21:00:00",
      "valor": 3.3333333333333335
    },
    {
      "fecha": "2026-02-10 22:00:00",
      "valor": 4.833333333333333
    },
    {
      "fecha": "2026-02-10 23:00:00",
      "valor": 4.333333333333333
    },
    {
      "fecha": "2026-02-11 00:00:00",
      "valor": 2.8
    },
    {
      "fecha": "2026-02-11 01:00:00",
      "valor": 2.5
    },
    {
      "fecha": "2026-02-11 02:00:00",
      "valor": 2.8333333333333335
    },
    {
      "fecha": "2026-02-11 03:00:00",
      "valor": 3.6666666666666665
    },
    {
      "fecha": "2026-02-11 04:00:00",
      "valor": 4.333333333333333
    },
    {
      "fecha": "2026-02-11 05:00:00",
      "valor": 5.5
    },
    {
      "fecha": "2026-02-11 06:00:00",
      "valor": 5.5
    },
    {
      "fecha": "2026-02-11 07:00:00",
      "valor": 7.833333333333333
    },
    {
      "fecha": "2026-02-11 08:00:00",
      "valor": 5.5
    },
    {
      "fecha": "2026-02-11 09:00:00",
      "valor": 5.8
    },
    {
      "fecha": "2026-02-11 10:00:00",
      "valor": 11.333333333333334
    },
    {
      "fecha": "2026-02-11 11:00:00",
      "valor": 14.571428571428571
    },
    {
      "fecha": "2026-02-11 12:00:00",
      "valor": 15.8
    },
    {
      "fecha": "2026-02-11 13:00:00",
      "valor": 12.0
    },
    {
      "fecha": "2026-02-11 14:00:00",
      "valor": 8.666666666666666
    },
    {
      "fecha": "2026-02-11 15:00:00",
      "valor": 9.166666666666666
    },
    {
      "fecha": "2026-02-11 16:00:00",
      "valor": 7.0
    },
    {
      "fecha": "2026-02-11 17:00:00",
      "valor": 6.666666666666667
    },
    {
      "fecha": "2026-02-11 18:00:00",
      "valor": 6.666666666666667
    },
    {
      "fecha": "2026-02-11 19:00:00",
      "valor": 7.166666666666667
    },
    {
      "fecha": "2026-02-11 20:00:00",
      "valor": 9.166666666666666
    },
    {
      "fecha": "2026-02-11 21:00:00",
      "valor": 5.0
    },
    {
      "fecha": "2026-02-11 22:00:00",
      "valor": 7.333333333333333
    },
    {
      "fecha": "2026-02-11 23:00:00",
      "valor": 8.2
    },
    {
      "fecha": "2026-02-12 00:00:00",
      "valor": 8.333333333333334
    },
    {
      "fecha": "2026-02-12 01:00:00",
      "valor": 8.666666666666666
    },
    {
      "fecha": "2026-02-12 02:00:00",
      "valor": 7.833333333333333
    },
    {
      "fecha": "2026-02-12 03:00:00",
      "valor": 8.833333333333334
    },
    {
      "fecha": "2026-02-12 04:00:00",
      "valor": 10.0
    },
    {
      "fecha": "2026-02-12 05:00:00",
      "valor": 10.333333333333334
    },
    {
      "fecha": "2026-02-12 06:00:00",
      "valor": 9.0
    },
    {
      "fecha": "2026-02-12 07:00:00",
      "valor": 11.0
    },
    {
      "fecha": "2026-02-12 08:00:00",
      "valor": 9.4
    },
    {
      "fecha": "2026-02-12 09:00:00",
      "valor": 11.0
    },
    {
      "fecha": "2026-02-12 10:00:00",
      "valor": 11.0
    },
    {
      "fecha": "2026-02-12 11:00:00",
      "valor": 11.5
    },
    {
      "fecha": "2026-02-12 12:00:00",
      "valor": 22.833333333333332
    },
    {
      "fecha": "2026-02-12 13:00:00",
      "valor": 22.666666666666668
    },
    {
      "fecha": "2026-02-12 14:00:00",
      "valor": 10.666666666666666
    },
    {
      "fecha": "2026-02-12 15:00:00",
      "valor": 10.5
    },
    {
      "fecha": "2026-02-12 16:00:00",
      "valor": 11.0
    },
    {
      "fecha": "2026-02-12 17:00:00",
      "valor": 9.5
    },
    {
      "fecha": "2026-02-12 18:00:00",
      "valor": 8.0
    },
    {
      "fecha": "2026-02-12 19:00:00",
      "valor": 9.0
    },
    {
      "fecha": "2026-02-12 20:00:00",
      "valor": 9.666666666666666
    },
    {
      "fecha": "2026-02-12 21:00:00",
      "valor": 6.833333333333333
    },
    {
      "fecha": "2026-02-12 22:00:00",
      "valor": 8.0
    },
    {
      "fecha": "2026-02-12 23:00:00",
      "valor": 5.666666666666667
    },
    {
      "fecha": "2026-02-13 00:00:00",
      "valor": 9.666666666666666
    },
    {
      "fecha": "2026-02-13 01:00:00",
      "valor": 7.0
    },
    {
      "fecha": "2026-02-13 02:00:00",
      "valor": 5.5
    },
    {
      "fecha": "2026-02-13 03:00:00",
      "valor": 8.666666666666666
    },
    {
      "fecha": "2026-02-13 04:00:00",
      "valor": 9.666666666666666
    },
    {
      "fecha": "2026-02-13 05:00:00",
      "valor": 9.333333333333334
    },
    {
      "fecha": "2026-02-13 06:00:00",
      "valor": 10.666666666666666
    },
    {
      "fecha": "2026-02-13 07:00:00",
      "valor": 10.833333333333334
    },
    {
      "fecha": "2026-02-13 08:00:00",
      "valor": 9.78888888888889
    },
    {
      "fecha": "2026-02-13 09:00:00",
      "valor": 10.105555555555556
    },
    {
      "fecha": "2026-02-13 10:00:00",
      "valor": 11.916666666666666
    },
    {
      "fecha": "2026-02-13 11:00:00",
      "valor": 11.0
    },
    {
      "fecha": "2026-02-13 12:00:00",
      "valor": 11.166666666666666
    },
    {
      "fecha": "2026-02-13 13:00:00",
      "valor": 18.166666666666668
    },
    {
      "fecha": "2026-02-13 14:00:00",
      "valor": 10.25
    },
    {
      "fecha": "2026-02-13 15:00:00",
      "valor": 11.422222222222222
    },
    {
      "fecha": "2026-02-13 16:00:00",
      "valor": 8.75
    },
    {
      "fecha": "2026-02-13 17:00:00",
      "valor": 12.0
    },
    {
      "fecha": "2026-02-13 18:00:00",
      "valor": 17.166666666666668
    },
    {
      "fecha": "2026-02-13 19:00:00",
      "valor": 15.166666666666666
    },
    {
      "fecha": "2026-02-13 20:00:00",
      "valor": 14.833333333333334
    },
    {
      "fecha": "2026-02-13 21:00:00",
      "valor": 11.0
    },
    {
      "fecha": "2026-02-13 22:00:00",
      "valor": 11.166666666666666
    },
    {
      "fecha": "2026-02-13 23:00:00",
      "valor": 11.2
    },
    {
      "fecha": "2026-02-14 00:00:00",
      "valor": 8.166666666666666
    },
    {
      "fecha": "2026-02-14 01:00:00",
      "valor": 4.833333333333333
    },
    {
      "fecha": "2026-02-14 02:00:00",
      "valor": 2.8333333333333335
    },
    {
      "fecha": "2026-02-14 03:00:00",
      "valor": 4.333333333333333
    },
    {
      "fecha": "2026-02-14 04:00:00",
      "valor": 9.333333333333334
    },
    {
      "fecha": "2026-02-14 05:00:00",
      "valor": 9.0
    },
    {
      "fecha": "2026-02-14 06:00:00",
      "valor": 14.0
    },
    {
      "fecha": "2026-02-14 07:00:00",
      "valor": 15.166666666666666
    },
    {
      "fecha": "2026-02-14 08:00:00",
      "valor": 15.4
    },
    {
      "fecha": "2026-02-14 09:00:00",
      "valor": 14.333333333333334
    },
    {
      "fecha": "2026-02-14 10:00:00",
      "valor": 13.333333333333334
    },
    {
      "fecha": "2026-02-14 11:00:00",
      "valor": 15.5
    },
    {
      "fecha": "2026-02-14 12:00:00",
      "valor": 17.333333333333332
    },
    {
      "fecha": "2026-02-14 13:00:00",
      "valor": 16.833333333333332
    },
    {
      "fecha": "2026-02-14 14:00:00",
      "valor": 12.833333333333334
    },
    {
      "fecha": "2026-02-14 15:00:00",
      "valor": 12.833333333333334
    },
    {
      "fecha": "2026-02-14 16:00:00",
      "valor": 12.333333333333334
    },
    {
      "fecha": "2026-02-14 17:00:00",
      "valor": 12.6
    },
    {
      "fecha": "2026-02-14 18:00:00",
      "valor": 14.0
    },
    {
      "fecha": "2026-02-14 19:00:00",
      "valor": 9.452380952380953
    },
    {
      "fecha": "2026-02-14 20:00:00",
      "valor": 9.404761904761903
    },
    {
      "fecha": "2026-02-14 21:00:00",
      "valor": 7.785714285714286
    },
    {
      "fecha": "2026-02-14 22:00:00",
      "valor": 8.666666666666666
    },
    {
      "fecha": "2026-02-14 23:00:00",
      "valor": 8.128571428571428
    },
    {
      "fecha": "2026-02-15 00:00:00",
      "valor": 9.138095238095238
    },
    {
      "fecha": "2026-02-15 01:00:00",
      "valor": 10.6
    },
    {
      "fecha": "2026-02-15 02:00:00",
      "valor": 7.666666666666667
    },
    {
      "fecha": "2026-02-15 03:00:00",
      "valor": 6.833333333333333
    },
    {
      "fecha": "2026-02-15 04:00:00",
      "valor": 6.833333333333333
    },
    {
      "fecha": "2026-02-15 05:00:00",
      "valor": 6.6
    },
    {
      "fecha": "2026-02-15 06:00:00",
      "valor": 6.666666666666667
    },
    {
      "fecha": "2026-02-15 07:00:00",
      "valor": 7.333333333333333
    },
    {
      "fecha": "2026-02-15 08:00:00",
      "valor": 8.833333333333334
    },
    {
      "fecha": "2026-02-15 09:00:00",
      "valor": 10.333333333333334
    },
    {
      "fecha": "2026-02-15 10:00:00",
      "valor": 13.166666666666666
    },
    {
      "fecha": "2026-02-15 11:00:00",
      "valor": 16.333333333333332
    },
    {
      "fecha": "2026-02-15 12:00:00",
      "valor": 13.0
    },
    {
      "fecha": "2026-02-15 13:00:00",
      "valor": 14.5
    },
    {
      "fecha": "2026-02-15 14:00:00",
      "valor": 12.2
    },
    {
      "fecha": "2026-02-15 15:00:00",
      "valor": 10.833333333333334
    },
    {
      "fecha": "2026-02-15 16:00:00",
      "valor": 9.833333333333334
    },
    {
      "fecha": "2026-02-15 17:00:00",
      "valor": 11.5
    },
    {
      "fecha": "2026-02-15 18:00:00",
      "valor": 9.0
    },
    {
      "fecha": "2026-02-15 19:00:00",
      "valor": 10.666666666666666
    },
    {
      "fecha": "2026-02-15 20:00:00",
      "valor": 10.333333333333334
    },
    {
      "fecha": "2026-02-15 21:00:00",
      "valor": 11.166666666666666
    },
    {
      "fecha": "2026-02-15 22:00:00",
      "valor": 8.166666666666666
    },
    {
      "fecha": "2026-02-15 23:00:00",
      "valor": 8.4
    },
    {
      "fecha": "2026-02-16 00:00:00",
      "valor": 11.833333333333334
    },
    {
      "fecha": "2026-02-16 01:00:00",
      "valor": 10.833333333333334
    },
    {
      "fecha": "2026-02-16 02:00:00",
      "valor": 7.833333333333333
    },
    {
      "fecha": "2026-02-16 03:00:00",
      "valor": 7.833333333333333
    },
    {
      "fecha": "2026-02-16 04:00:00",
      "valor": 11.333333333333334
    },
    {
      "fecha": "2026-02-16 05:00:00",
      "valor": 12.666666666666666
    },
    {
      "fecha": "2026-02-16 06:00:00",
      "valor": 13.166666666666666
    },
    {
      "fecha": "2026-02-16 07:00:00",
      "valor": 12.0
    }
  ],
  "pronosticos": [
    {
      "fecha": "2026-02-16 08:00:00",
      "pronostico": 11.5227806422324,
      "confianza_80_min": 8.266191657808307,
      "confianza_80_max": 14.779369626656493,
      "confianza_95_min": 6.542257584458522,
      "confianza_95_max": 16.503303700006278
    },
    {
      "fecha": "2026-02-16 09:00:00",
      "pronostico": 10.441907027305815,
      "confianza_80_min": 6.385401462053902,
      "confianza_80_max": 14.498412592557727,
      "confianza_95_min": 4.238017129515082,
      "confianza_95_max": 16.645796925096548
    },
    {
      "fecha": "2026-02-16 10:00:00",
      "pronostico": 11.297658959807608,
      "confianza_80_min": 6.825296543021469,
      "confianza_80_max": 15.770021376593746,
      "confianza_95_min": 4.45777089101473,
      "confianza_95_max": 18.137547028600487
    },
    {
      "fecha": "2026-02-16 11:00:00",
      "pronostico": 12.19845902710001,
      "confianza_80_min": 7.491819868629355,
      "confianza_80_max": 16.905098185570665,
      "confianza_95_min": 5.000275600974461,
      "confianza_95_max": 19.39664245322556
    },
    {
      "fecha": "2026-02-16 12:00:00",
      "pronostico": 13.462576944276545,
      "confianza_80_min": 8.619410500392435,
      "confianza_80_max": 18.305743388160657,
      "confianza_95_min": 6.0555930535331886,
      "confianza_95_max": 20.869560835019904
    },
    {
      "fecha": "2026-02-16 13:00:00",
      "pronostico": 12.806486228394421,
      "confianza_80_min": 7.882385915157757,
      "confianza_80_max": 17.730586541631084,
      "confianza_95_min": 5.275724665862207,
      "confianza_95_max": 20.337247790926636
    },
    {
      "fecha": "2026-02-16 14:00:00",
      "pronostico": 9.687367233150987,
      "confianza_80_min": 4.714837930917024,
      "confianza_80_max": 14.659896535384949,
      "confianza_95_min": 2.082539923446081,
      "confianza_95_max": 17.292194542855892
    },
    {
      "fecha": "2026-02-16 15:00:00",
      "pronostico": 9.818990511574857,
      "confianza_80_min": 4.817326927109874,
      "confianza_80_max": 14.820654096039839,
      "confianza_95_min": 2.1696061622443485,
      "confianza_95_max": 17.468374860905364
    },
    {
      "fecha": "2026-02-16 16:00:00",
      "pronostico": 9.940244138168236,
      "confianza_80_min": 4.920998713874198,
      "confianza_80_max": 14.959489562462274,
      "confianza_95_min": 2.2639706852125796,
      "confianza_95_max": 17.61651759112389
    },
    {
      "fecha": "2026-02-16 17:00:00",
      "pronostico": 9.767297286608207,
      "confianza_80_min": 4.737421882034068,
      "confianza_80_max": 14.797172691182345,
      "confianza_95_min": 2.07476668172397,
      "confianza_95_max": 17.459827891492445
    },
    {
      "fecha": "2026-02-16 18:00:00",
      "pronostico": 10.122044148630302,
      "confianza_80_min": 5.085737506351009,
      "confianza_80_max": 15.158350790909594,
      "confianza_95_min": 2.4196778144496305,
      "confianza_95_max": 17.824410482810972
    },
    {
      "fecha": "2026-02-16 19:00:00",
      "pronostico": 10.101834636210778,
      "confianza_80_min": 5.0641441481568625,
      "confianza_80_max": 15.139525124264694,
      "confianza_95_min": 2.3973518925532353,
      "confianza_95_max": 17.80631737986832
    },
    {
      "fecha": "2026-02-16 20:00:00",
      "pronostico": 10.02888028930413,
      "confianza_80_min": 4.973983086193085,
      "confianza_80_max": 15.083777492415175,
      "confianza_95_min": 2.298082145852365,
      "confianza_95_max": 17.759678432755894
    },
    {
      "fecha": "2026-02-16 21:00:00",
      "pronostico": 9.278675101354414,
      "confianza_80_min": 4.21403829854688,
      "confianza_80_max": 14.343311904161949,
      "confianza_95_min": 1.5329815255672026,
      "confianza_95_max": 17.024368677141627
    },
    {
      "fecha": "2026-02-16 22:00:00",
      "pronostico": 10.391903424707621,
      "confianza_80_min": 5.3213705884022735,
      "confianza_80_max": 15.462436261012968,
      "confianza_95_min": 2.637192643824611,
      "confianza_95_max": 18.14661420559063
    },
    {
      "fecha": "2026-02-16 23:00:00",
      "pronostico": 11.493188589570307,
      "confianza_80_min": 6.419084309596065,
      "confianza_80_max": 16.56729286954455,
      "confianza_95_min": 3.7330157569431117,
      "confianza_95_max": 19.253361422197504
    },
    {
      "fecha": "2026-02-17 00:00:00",
      "pronostico": 12.913415089032204,
      "confianza_80_min": 7.837146657388198,
      "confianza_80_max": 17.98968352067621,
      "confianza_95_min": 5.149932472043725,
      "confianza_95_max": 20.676897706020682
    },
    {
      "fecha": "2026-02-17 01:00:00",
      "pronostico": 12.378878991216407,
      "confianza_80_min": 7.301298878151334,
      "confianza_80_max": 17.45645910428148,
      "confianza_95_min": 4.613390330605805,
      "confianza_95_max": 20.14436765182701
    },
    {
      "fecha": "2026-02-17 02:00:00",
      "pronostico": 9.354409021394527,
      "confianza_80_min": 4.276033797574054,
      "confianza_80_max": 14.432784245215,
      "confianza_95_min": 1.5877043438196434,
      "confianza_95_max": 17.12111369896941
    },
    {
      "fecha": "2026-02-17 03:00:00",
      "pronostico": 9.559731169970432,
      "confianza_80_min": 4.480873929181167,
      "confianza_80_max": 14.638588410759697,
      "confianza_95_min": 1.792289311056794,
      "confianza_95_max": 17.32717302888407
    },
    {
      "fecha": "2026-02-17 04:00:00",
      "pronostico": 9.738370738336537,
      "confianza_80_min": 4.659221272301535,
      "confianza_80_max": 14.817520204371538,
      "confianza_95_min": 1.970481959476472,
      "confianza_95_max": 17.5062595171966
    },
    {
      "fecha": "2026-02-17 05:00:00",
      "pronostico": 9.61010769680438,
      "confianza_80_min": 4.530781068779879,
      "confianza_80_max": 14.689434324828882,
      "confianza_95_min": 1.8419479720626324,
      "confianza_95_max": 17.378267421546127
    },
    {
      "fecha": "2026-02-17 06:00:00",
      "pronostico": 9.99964779941691,
      "confianza_80_min": 4.920205318087878,
      "confianza_80_max": 15.079090280745945,
      "confianza_95_min": 2.231310892335821,
      "confianza_95_max": 17.767984706498
    },
    {
      "fecha": "2026-02-17 07:00:00",
      "pronostico": 10.006530193216415,
      "confianza_80_min": 4.929763858683912,
      "confianza_80_max": 15.083296527748917,
      "confianza_95_min": 2.2422860994715643,
      "confianza_95_max": 17.770774286961267
    },
    {
      "fecha": "2026-02-17 08:00:00",
      "pronostico": 9.954671075444079,
      "confianza_80_min": 4.870628405037647,
      "confianza_80_max": 15.038713745850512,
      "confianza_95_min": 2.179298786286929,
      "confianza_95_max": 17.73004336460123
    },
    {
      "fecha": "2026-02-17 09:00:00",
      "pronostico": 9.220891778261572,
      "confianza_80_min": 4.132898108362693,
      "confianza_80_max": 14.308885448160453,
      "confianza_95_min": 1.4394769568206423,
      "confianza_95_max": 17.002306599702504
    },
    {
      "fecha": "2026-02-17 10:00:00",
      "pronostico": 10.346910192008126,
      "confianza_80_min": 5.256522514805972,
      "confianza_80_max": 15.43729786921028,
      "confianza_95_min": 2.561834052350048,
      "confianza_95_max": 18.131986331666205
    },
    {
      "fecha": "2026-02-17 11:00:00",
      "pronostico": 11.458154415687677,
      "confianza_80_min": 6.36631579402783,
      "confianza_80_max": 16.549993037347523,
      "confianza_95_min": 3.6708592479724347,
      "confianza_95_max": 19.24544958340292
    },
    {
      "fecha": "2026-02-17 12:00:00",
      "pronostico": 12.886135579070427,
      "confianza_80_min": 7.793417447460543,
      "confianza_80_max": 17.978853710680312,
      "confianza_95_min": 5.097495316961433,
      "confianza_95_max": 20.674775841179418
    },
    {
      "fecha": "2026-02-17 13:00:00",
      "pronostico": 12.357637683622062,
      "confianza_80_min": 7.264386376882611,
      "confianza_80_max": 17.450888990361513,
      "confianza_95_min": 4.568182000519095,
      "confianza_95_max": 20.14709336672503
    },
    {
      "fecha": "2026-02-17 14:00:00",
      "pronostico": 9.337869386007025,
      "confianza_80_min": 4.244294841033321,
      "confianza_80_max": 14.431443930980729,
      "confianza_95_min": 1.547919352684687,
      "confianza_95_max": 17.127819419329363
    },
    {
      "fecha": "2026-02-17 15:00:00",
      "pronostico": 9.54685251183997,
      "confianza_80_min": 4.453081996765589,
      "confianza_80_max": 14.640623026914351,
      "confianza_95_min": 1.7566027681121357,
      "confianza_95_max": 17.337102255567807
    },
    {
      "fecha": "2026-02-17 16:00:00",
      "pronostico": 9.728342715870781,
      "confianza_80_min": 4.634453387879511,
      "confianza_80_max": 14.822232043862051,
      "confianza_95_min": 1.9379112634671039,
      "confianza_95_max": 17.518774168274458
    },
    {
      "fecha": "2026-02-17 17:00:00",
      "pronostico": 9.602299334042124,
      "confianza_80_min": 4.5083379775349,
      "confianza_80_max": 14.696260690549348,
      "confianza_95_min": 1.8117577235293822,
      "confianza_95_max": 17.392840944554866
    },
    {
      "fecha": "2026-02-17 18:00:00",
      "pronostico": 9.993567784215989,
      "confianza_80_min": 4.899553782021858,
      "confianza_80_max": 15.08758178641012,
      "confianza_95_min": 2.2029456590731264,
      "confianza_95_max": 17.78418990935885
    },
    {
      "fecha": "2026-02-17 19:00:00",
      "pronostico": 10.001795963267195,
      "confianza_80_min": 4.9105011916756425,
      "confianza_80_max": 15.093090734858748,
      "confianza_95_min": 2.215332542455865,
      "confianza_95_max": 17.788259384078525
    },
    {
      "fecha": "2026-02-17 20:00:00",
      "pronostico": 9.950984746961103,
      "confianza_80_min": 4.852829474119101,
      "confianza_80_max": 15.049140019803104,
      "confianza_95_min": 2.154029094913602,
      "confianza_95_max": 17.747940399008606
    },
    {
      "fecha": "2026-02-17 21:00:00",
      "pronostico": 9.218021402755912,
      "confianza_80_min": 4.116155244584588,
      "confianza_80_max": 14.319887560927237,
      "confianza_95_min": 1.4153904413476512,
      "confianza_95_max": 17.020652364164174
    },
    {
      "fecha": "2026-02-17 22:00:00",
      "pronostico": 10.344675161792686,
      "confianza_80_min": 5.24056039860282,
      "confianza_80_max": 15.448789924982552,
      "confianza_95_min": 2.538605255772061,
      "confianza_95_max": 18.15074506781331
    },
    {
      "fecha": "2026-02-17 23:00:00",
      "pronostico": 11.456414099811205,
      "confianza_80_min": 6.350936484084348,
      "confianza_80_max": 16.561891715538064,
      "confianza_95_min": 3.6482598907000465,
      "confianza_95_max": 19.264568308922364
    },
    {
      "fecha": "2026-02-18 00:00:00",
      "pronostico": 12.88478047463874,
      "confianza_80_min": 7.778476735140963,
      "confianza_80_max": 17.991084214136517,
      "confianza_95_min": 5.075362818249057,
      "confianza_95_max": 20.694198131028422
    },
    {
      "fecha": "2026-02-18 01:00:00",
      "pronostico": 12.3565825257363,
      "confianza_80_min": 7.249777970404448,
      "confianza_80_max": 17.463387081068152,
      "confianza_95_min": 4.546398937624427,
      "confianza_95_max": 20.166766113848173
    },
    {
      "fecha": "2026-02-18 02:00:00",
      "pronostico": 9.337047782787485,
      "confianza_80_min": 4.2299396054811735,
      "confianza_80_max": 14.444155960093795,
      "confianza_95_min": 1.526399844936706,
      "confianza_95_max": 17.147695720638264
    },
    {
      "fecha": "2026-02-18 03:00:00",
      "pronostico": 9.546212766964377,
      "confianza_80_min": 4.4389205117459225,
      "confianza_80_max": 14.65350502218283,
      "confianza_95_min": 1.735283306240972,
      "confianza_95_max": 17.35714222768778
    },
    {
      "fecha": "2026-02-18 04:00:00",
      "pronostico": 9.727844575775762,
      "confianza_80_min": 4.620440717462039,
      "confianza_80_max": 14.835248434089486,
      "confianza_95_min": 1.9167444328471541,
      "confianza_95_max": 17.53894471870437
    },
    {
      "fecha": "2026-02-18 05:00:00",
      "pronostico": 9.60191145511768,
      "confianza_80_min": 4.494439939441256,
      "confianza_80_max": 14.709382970794103,
      "confianza_95_min": 1.7907078391820175,
      "confianza_95_max": 17.41311507105334
    },
    {
      "fecha": "2026-02-18 06:00:00",
      "pronostico": 9.99326576062557,
      "confianza_80_min": 4.885744245598562,
      "confianza_80_max": 15.100787275652579,
      "confianza_95_min": 2.1819856772819373,
      "confianza_95_max": 17.804545843969205
    },
    {
      "fecha": "2026-02-18 07:00:00",
      "pronostico": 10.001560791301356,
      "confianza_80_min": 4.896753456866096,
      "confianza_80_max": 15.106368125736616,
      "confianza_95_min": 2.1944316889641753,
      "confianza_95_max": 17.808689893638537
    },
    {
      "fecha": "2026-02-18 08:00:00",
      "pronostico": 9.950801629299864,
      "confianza_80_min": 4.839171281422085,
      "confianza_80_max": 15.062431977177642,
      "confianza_95_min": 2.133237628381223,
      "confianza_95_max": 17.768365630218504
    },
    {
      "fecha": "2026-02-18 09:00:00",
      "pronostico": 9.217878817402518,
      "confianza_80_min": 4.102558579345669,
      "confianza_80_max": 14.333199055459367,
      "confianza_95_min": 1.3946716164345592,
      "confianza_95_max": 17.04108601837048
    },
    {
      "fecha": "2026-02-18 10:00:00",
      "pronostico": 10.344564137094878,
      "confianza_80_min": 5.227008005195342,
      "confianza_80_max": 15.462120268994415,
      "confianza_95_min": 2.5179374315804433,
      "confianza_95_max": 18.171190842609313
    },
    {
      "fecha": "2026-02-18 11:00:00",
      "pronostico": 11.456327649953417,
      "confianza_80_min": 6.337416365646303,
      "confianza_80_max": 16.575238934260533,
      "confianza_95_min": 3.6276284176801497,
      "confianza_95_max": 19.285026882226685
    },
    {
      "fecha": "2026-02-18 12:00:00",
      "pronostico": 12.88471316008568,
      "confianza_80_min": 7.7649804181601745,
      "confianza_80_max": 18.004445902011184,
      "confianza_95_min": 5.054757616798358,
      "confianza_95_max": 20.714668703373
    },
    {
      "fecha": "2026-02-18 13:00:00",
      "pronostico": 12.356530110970452,
      "confianza_80_min": 7.236299381409063,
      "confianza_80_max": 17.47676084053184,
      "confianza_95_min": 4.525812961316817,
      "confianza_95_max": 20.187247260624087
    },
    {
      "fecha": "2026-02-18 14:00:00",
      "pronostico": 9.337006969804941,
      "confianza_80_min": 4.216474332681406,
      "confianza_80_max": 14.457539606928476,
      "confianza_95_min": 1.505828092379769,
      "confianza_95_max": 17.168185847230113
    },
    {
      "fecha": "2026-02-18 15:00:00",
      "pronostico": 9.54618098776023,
      "confianza_80_min": 4.4254653120551115,
      "confianza_80_max": 14.66689666346535,
      "confianza_95_min": 1.7147221769813568,
      "confianza_95_max": 17.377639798539104
    },
    {
      "fecha": "2026-02-18 16:00:00",
      "pronostico": 9.727819830761966,
      "confianza_80_min": 4.60699318206405,
      "confianza_80_max": 14.848646479459882,
      "confianza_95_min": 1.8961913014364598,
      "confianza_95_max": 17.559448360087472
    },
    {
      "fecha": "2026-02-18 17:00:00",
      "pronostico": 9.60189218730641,
      "confianza_80_min": 4.480998263244528,
      "confianza_80_max": 14.722786111368292,
      "confianza_95_min": 1.7701607691904995,
      "confianza_95_max": 17.43362360542232
    },
    {
      "fecha": "2026-02-18 18:00:00",
      "pronostico": 9.993250757661572,
      "confianza_80_min": 4.872307088017522,
      "confianza_80_max": 15.114194427305623,
      "confianza_95_min": 2.1614432602429936,
      "confianza_95_max": 17.82505825508015
    },
    {
      "fecha": "2026-02-18 19:00:00",
      "pronostico": 10.001549109179003,
      "confianza_80_min": 4.883312607780394,
      "confianza_80_max": 15.119785610577612,
      "confianza_95_min": 2.1738818683086656,
      "confianza_95_max": 17.82921635004934
    },
    {
      "fecha": "2026-02-18 20:00:00",
      "pronostico": 9.95079253296512,
      "confianza_80_min": 4.82575185471641,
      "confianza_80_max": 15.075833211213832,
      "confianza_95_min": 2.112719201595434,
      "confianza_95_max": 17.78886586433481
    },
    {
      "fecha": "2026-02-18 21:00:00",
      "pronostico": 9.2178717345024,
      "confianza_80_min": 4.0891513697615265,
      "confianza_80_max": 14.346592099243274,
      "confianza_95_min": 1.3741708082758697,
      "confianza_95_max": 17.06157266072893
    },
    {
      "fecha": "2026-02-18 22:00:00",
      "pronostico": 10.344558621964282,
      "confianza_80_min": 5.213608539382473,
      "confianza_80_max": 15.47550870454609,
      "confianza_95_min": 2.4974476365708664,
      "confianza_95_max": 18.191669607357696
    },
    {
      "fecha": "2026-02-18 23:00:00",
      "pronostico": 11.456323355573291,
      "confianza_80_min": 6.324021861251563,
      "confianza_80_max": 16.58862484989502,
      "confianza_95_min": 3.6071455642785466,
      "confianza_95_max": 19.305501146868036
    },
    {
      "fecha": "2026-02-19 00:00:00",
      "pronostico": 12.88470981624815,
      "confianza_80_min": 7.751589130868165,
      "confianza_80_max": 18.017830501628136,
      "confianza_95_min": 5.034279180343943,
      "confianza_95_max": 20.735140452152358
    },
    {
      "fecha": "2026-02-19 01:00:00",
      "pronostico": 12.356527507276999,
      "confianza_80_min": 7.222910207962138,
      "confianza_80_max": 17.49014480659186,
      "confianza_95_min": 4.505337365900873,
      "confianza_95_max": 20.207717648653123
    },
    {
      "fecha": "2026-02-19 02:00:00",
      "pronostico": 9.337004942427852,
      "confianza_80_min": 4.203086568238108,
      "confianza_80_max": 14.470923316617595,
      "confianza_95_min": 1.4853543467654644,
      "confianza_95_max": 17.188655538090238
    },
    {
      "fecha": "2026-02-19 03:00:00",
      "pronostico": 9.546179409134352,
      "confianza_80_min": 4.41207850115302,
      "confianza_80_max": 14.680280317115685,
      "confianza_95_min": 1.6942496521279393,
      "confianza_95_max": 17.398109166140763
    },
    {
      "fecha": "2026-02-19 04:00:00",
      "pronostico": 9.727818601558146,
      "confianza_80_min": 4.593607026612157,
      "confianza_80_max": 14.862030176504135,
      "confianza_95_min": 1.875719594034754,
      "confianza_95_max": 17.57991760908154
    },
    {
      "fecha": "2026-02-19 05:00:00",
      "pronostico": 9.601891230181575,
      "confianza_80_min": 4.467612565390377,
      "confianza_80_max": 14.736169894972774,
      "confianza_95_min": 1.7496896175942327,
      "confianza_95_max": 17.45409284276892
    },
    {
      "fecha": "2026-02-19 06:00:00",
      "pronostico": 9.99325001239221,
      "confianza_80_min": 4.85892173777751,
      "confianza_80_max": 15.127578287006909,
      "confianza_95_min": 2.140972528127161,
      "confianza_95_max": 17.845527496657258
    },
    {
      "fecha": "2026-02-19 07:00:00",
      "pronostico": 10.001548528871812,
      "confianza_80_min": 4.869920366725771,
      "confianza_80_max": 15.133176691017852,
      "confianza_95_min": 2.153400510275616,
      "confianza_95_max": 17.849696547468007
    }
  ]
}